botscheduler/__init__.py
botscheduler/botscheduler.py
botscheduler-0.1.0.dist-info/METADATA
botscheduler-0.1.0.dist-info/WHEEL
botscheduler-0.1.0.dist-info/top_level.txt
botscheduler-0.1.0.dist-info/RECORD
