Metadata-Version: 2.1
Name: botscheduler
Version: 0.1.0
Summary: A simple Scheduler.
Home-page: https://github.com/duducosmos/botscheduler
Author: Eduardo S. Pereira
Author-email: pereira.somoza@gmail.com
License: Apache License 2.0
Platform: UNKNOWN
